pkn.py
py_kr_number-0.0.4.dist-info/LICENSE
py_kr_number-0.0.4.dist-info/METADATA
py_kr_number-0.0.4.dist-info/WHEEL
py_kr_number-0.0.4.dist-info/top_level.txt
py_kr_number-0.0.4.dist-info/RECORD
