Metadata-Version: 2.1
Name: py-kr-number
Version: 0.0.4
Summary: Simple Korean unit conversion module
Home-page: https://github.com/yeokyoomin/py_kr_number.git
Author: yeokyoomin
Author-email: msdhgoom@gmail.com
License: yeokyoomin
License-File: LICENSE
